{"authorDailyContributionsMap":{"Amanda-HUANG88":[{"date":"2025-08-28T00:00:00","commitResults":[{"hash":"2ddc4df512bde5a8a7160b1af13f45b0f4f624fa","isMergeCommit":false,"messageTitle":"Add Increment: Level-0","messageBody":"","tags":["Level-0"],"fileTypesAndContributionMap":{"java":{"insertions":11,"deletions":10}}},{"hash":"a1160c65b027ef3cac25a9eeabf5928564fe38f2","isMergeCommit":false,"messageTitle":"Add Increment: Level-1 Echo","messageBody":"","tags":["Level-1"],"fileTypesAndContributionMap":{"java":{"insertions":18,"deletions":2}}},{"hash":"9c9154ddfab9d4ca89ea92756a6df7e44b7193b2","isMergeCommit":false,"messageTitle":"Add Increment: Level-2 Add, List","messageBody":"","tags":["Level-2"],"fileTypesAndContributionMap":{"java":{"insertions":20,"deletions":11}}},{"hash":"f021c534c2383c6fe70472adcaf743a868b5f9c9","isMergeCommit":false,"messageTitle":"Add Increment: Level-3 Mark as Done","messageBody":"","tags":["Level-3"],"fileTypesAndContributionMap":{"java":{"insertions":60,"deletions":6}}}]},{"date":"2025-09-03T00:00:00","commitResults":[{"hash":"95cfa099024480098d8743fdfbd2967c6e87f4d2","isMergeCommit":false,"messageTitle":"Level 4. ToDos, Events, Deadlines","messageBody":"","tags":["Level-4","A-CodingStandard","A-CodeQuality"],"fileTypesAndContributionMap":{"java":{"insertions":132,"deletions":41}}},{"hash":"38564813570b13e93157885fb3f27c8ffb74b130","isMergeCommit":false,"messageTitle":"A-TextUiTesting","messageBody":"","tags":["A-TextUiTesting"],"fileTypesAndContributionMap":{"txt":{"insertions":8,"deletions":0},"bat":{"insertions":2,"deletions":2}}}]},{"date":"2025-09-11T00:00:00","commitResults":[{"hash":"413d778a8e0ca61526071550c2699b3c47023c25","isMergeCommit":false,"messageTitle":"Level-5: Handle Errors","messageBody":"","fileTypesAndContributionMap":{"java":{"insertions":60,"deletions":23}}},{"hash":"82724bdf1c025ee130ecfe4ba2c836fee58cc636","isMergeCommit":true,"messageTitle":"Merge branch \u0027branch-Level-5\u0027 into master (Level-5)","messageBody":"","tags":["Level-5"],"fileTypesAndContributionMap":{}},{"hash":"e76cf1c2aa3ca463dc7f5f806661783fc31c19f1","isMergeCommit":false,"messageTitle":" add exception class","messageBody":"","tags":["A-Exceptions"],"fileTypesAndContributionMap":{"java":{"insertions":5,"deletions":5}}},{"hash":"ac9139e5e8f496d22155c51f027976b480b0aff2","isMergeCommit":false,"messageTitle":"feat(Level-6): Organize classes into packages","messageBody":"","fileTypesAndContributionMap":{"txt":{"insertions":4,"deletions":5},"java":{"insertions":16,"deletions":0}}},{"hash":"8327ed841c3d33115abd1c932e0b8281f80ddd4f","isMergeCommit":true,"messageTitle":"Merge branch \u0027branch-Level-6\u0027 for Level 6: Packages","messageBody":"","tags":["Level-6","A-Packages"],"fileTypesAndContributionMap":{}}]},{"date":"2025-09-17T00:00:00","commitResults":[{"hash":"79a13a8b385ae031f013c4463f9e68e7a8495ebf","isMergeCommit":false,"messageTitle":"Implement delete command for Level 6","messageBody":"","fileTypesAndContributionMap":{"java":{"insertions":65,"deletions":59}}},{"hash":"20f86642f2366e069f306e63619bcccc3a404886","isMergeCommit":false,"messageTitle":"Implement Level 6 feature","messageBody":"","fileTypesAndContributionMap":{"java":{"insertions":65,"deletions":59}}},{"hash":"5a0dc0a400aaebb032ff02722ee151691fefb765","isMergeCommit":false,"messageTitle":"Implement Level 7 feature","messageBody":"","fileTypesAndContributionMap":{"java":{"insertions":99,"deletions":2}}}]},{"date":"2025-09-18T00:00:00","commitResults":[{"hash":"49acf9225878e7cc2c6240f2f8c3e1d5b33b985b","isMergeCommit":true,"messageTitle":"Merge branch-Level-7 after resolving conflicts","messageBody":"","tags":["Level-7","A-Jar"],"fileTypesAndContributionMap":{}}]},{"date":"2025-10-03T00:00:00","commitResults":[{"hash":"48cb1e27ff8bbbe0d543575d66d96f3430b28c34","isMergeCommit":false,"messageTitle":"make the code more OOP","messageBody":"","fileTypesAndContributionMap":{"java":{"insertions":479,"deletions":207}}},{"hash":"796f213055fc08bd3948e6d20ab6043418d21d68","isMergeCommit":true,"messageTitle":"resolve conflict","messageBody":"","tags":["A-MoreOOP"],"fileTypesAndContributionMap":{}},{"hash":"af85a9e9b0ce571dd4a696925e99d784dc37eaa7","isMergeCommit":false,"messageTitle":"Level-9: Implement Find command to search tasks by keyword.","messageBody":"","fileTypesAndContributionMap":{"java":{"insertions":47,"deletions":1}}},{"hash":"32eae19d005e68ec41fde0486cdcd8116f57f7c9","isMergeCommit":false,"messageTitle":"A-JavaDoc: Added JavaDoc to all public classes and methods.","messageBody":"","fileTypesAndContributionMap":{"txt":{"insertions":2,"deletions":0},"java":{"insertions":98,"deletions":0}}},{"hash":"6b94cb2411b88370ae2d9c7fca35a82db917c1d7","isMergeCommit":true,"messageTitle":"Merge pull request #1 from Amanda-HUANG88/branch-A-JavaDoc","messageBody":"branch-A-JavaDoc","fileTypesAndContributionMap":{}},{"hash":"b48998c70a65e29ef5ebea81266449971d291e13","isMergeCommit":false,"messageTitle":"Level-9: Implement Find command to search tasks by keyword.","messageBody":"","fileTypesAndContributionMap":{"java":{"insertions":47,"deletions":1}}},{"hash":"5d2618b2b94880a830f3396fe5cca1617f8b7f83","isMergeCommit":true,"messageTitle":"Merge pull request #2 from Amanda-HUANG88/branch-Level-9","messageBody":"branch-Level-9","fileTypesAndContributionMap":{}}]}]},"authorFileTypeContributionMap":{"Amanda-HUANG88":{"java":744,"md":0,"fxml":0,"sh":0,"bat":2,"gradle":0,"txt":9}},"authorContributionVariance":{"Amanda-HUANG88":16103.028},"authorDisplayNameMap":{"Amanda-HUANG88":"CS2113-T10-2 HUAN..NGRU"}}
