{"authorDailyContributionsMap":{"Emannuel-Tan":[{"date":"2025-08-18T00:00:00","commitResults":[{"hash":"6ee28f016c02358d994115009ce8e1716f8d0e93","isMergeCommit":false,"messageTitle":"Level-0: Rename Chatbot Duke-\u003eTaskMaster \u0026 Added greet and exit","messageBody":"","tags":["Level-0"],"fileTypesAndContributionMap":{"java":{"insertions":15,"deletions":10}}}]},{"date":"2025-08-23T00:00:00","commitResults":[{"hash":"cb764c6882c31e162ed4f5684bd48fc0c61f1d12","isMergeCommit":false,"messageTitle":"TaskMaster.java: Change Start and Ending Messages to use constants","messageBody":"","fileTypesAndContributionMap":{"java":{"insertions":17,"deletions":9}}},{"hash":"d69c8b8e5c928eca0e913e12cfcc9cff3c2d39d5","isMergeCommit":false,"messageTitle":"TaskMaster.java: Add ability for TaskMaster to echo commands entered by user until bye command","messageBody":"","tags":["Level-1"],"fileTypesAndContributionMap":{"java":{"insertions":9,"deletions":0}}},{"hash":"d1fef7df6f7cc3e7e38cff5933faa6ae086c7b6f","isMergeCommit":false,"messageTitle":"TaskMaster.java: Change Taskmaster from echo text to save text entered and display all tasks saved with \"list\" command","messageBody":"","tags":["Level-2"],"fileTypesAndContributionMap":{"java":{"insertions":26,"deletions":2}}},{"hash":"1e41dbbb756323141536ca03e312a82fdf98c065","isMergeCommit":false,"messageTitle":"TaskMaster.java: Add Task.java \u0026 Intergrate use of Task class in Main code","messageBody":"","tags":["A-Classes"],"fileTypesAndContributionMap":{"java":{"insertions":48,"deletions":12}}},{"hash":"9bcb9055414a76fa75364bec50b670801e42d8c1","isMergeCommit":false,"messageTitle":"TaskMaster.java: Add ability to mark and unmark tasks","messageBody":"","fileTypesAndContributionMap":{"java":{"insertions":18,"deletions":2}}},{"hash":"45a58cd91c76d94a39040f0de6fe7c29081fa5cc","isMergeCommit":false,"messageTitle":"TaskMaster.java: Add Methods to mark \u0026 unmark Tasks to clean up code","messageBody":"","tags":["Level-3","A-CodingStandard"],"fileTypesAndContributionMap":{"java":{"insertions":24,"deletions":14}}}]},{"date":"2025-08-30T00:00:00","commitResults":[{"hash":"73a32f5983e6c22c0ef80fe56617f6c12fa7d623","isMergeCommit":false,"messageTitle":"TaskMaster.java: Move start \u0026 end message from main method to 2 seperate methods","messageBody":"","fileTypesAndContributionMap":{"java":{"insertions":22,"deletions":12}}},{"hash":"9ab51a45d468a2a092fd8588428d587e25eb479d","isMergeCommit":false,"messageTitle":"TaskMaster.java: Extract addTask as a method","messageBody":"","fileTypesAndContributionMap":{"java":{"insertions":9,"deletions":4}}},{"hash":"b73f1fe850438609ab8f8b4d07d20f4098ea3007","isMergeCommit":false,"messageTitle":"TaskMaster.java: Extract Magic Numbers","messageBody":"","fileTypesAndContributionMap":{"java":{"insertions":10,"deletions":4}}},{"hash":"32d926449b08fb14d7eb276889289ea4cbb8be0e","isMergeCommit":false,"messageTitle":"Add enum TaskType in TaskType.java","messageBody":"","fileTypesAndContributionMap":{"java":{"insertions":3,"deletions":0}}},{"hash":"7df7ee72e42fd7a4fb10ceb03bb48d185f00c439","isMergeCommit":false,"messageTitle":"Add ToDo.java that inherits from Task class, ToDo overwrites getStatus Method","messageBody":"","fileTypesAndContributionMap":{"java":{"insertions":13,"deletions":0}}},{"hash":"342710cd2242f4bc0dc477ca23ca8f0827a81d15","isMergeCommit":false,"messageTitle":"TaskMaster.java: Change startMessage from 2 new lines at the end of method to 1 new line at end of method","messageBody":"","fileTypesAndContributionMap":{"java":{"insertions":1,"deletions":1}}},{"hash":"33ce9b52185f8f1123ae9d1a328bf3cacda3ff50","isMergeCommit":false,"messageTitle":"TaskMaster.java: Change addTask method to addToDo method which is called when given \"todo\" command, Add method addTaskOutput that echos task that user inputs \u0026 current total number of Tasks in the list","messageBody":"","fileTypesAndContributionMap":{"java":{"insertions":22,"deletions":7}}},{"hash":"9582a01c6b1c7693260854a31e468da413c51fba","isMergeCommit":false,"messageTitle":"TaskMaster.java: Add method unknownCommand that outputs possilble commands to user when user inputs unknown command \u0026 Change String variable \u0027spacing\u0027 to a constant","messageBody":"","fileTypesAndContributionMap":{"java":{"insertions":20,"deletions":10}}},{"hash":"fa810331563da2904d78dc8c95ae4bd188d4fbc3","isMergeCommit":false,"messageTitle":"ToDo.java: Change type from local TaskType variable to protected TaskType that can be set by child classes","messageBody":"","fileTypesAndContributionMap":{"java":{"insertions":2,"deletions":1}}},{"hash":"618d34563c2c9eafc35b392f9e1d1901632f59ad","isMergeCommit":false,"messageTitle":"Add class Deadline.java that inherits from class ToDo.java","messageBody":"","fileTypesAndContributionMap":{"java":{"insertions":15,"deletions":0}}},{"hash":"c1d94f6e2b4a756d63bec129c1662cbdc970134c","isMergeCommit":false,"messageTitle":"TaskMaster.java: Change one of the input parameter type of addTaskOutput method from String to Task","messageBody":"","fileTypesAndContributionMap":{"java":{"insertions":8,"deletions":5}}},{"hash":"24ab0119542079d5b5cc1752a3e874622f89a053","isMergeCommit":false,"messageTitle":"TaskMaster.java: Add addDeadline Method \u0026 update unknownCommand Method accordingly","messageBody":"","fileTypesAndContributionMap":{"java":{"insertions":31,"deletions":7}}},{"hash":"a68e248d43d769bda5913afe648c6947ec00f4ea","isMergeCommit":false,"messageTitle":"TaskMaster.java: Fix bug of wrong number of tasks shown in addTaskOutput Method introduced by previous parameter change commit","messageBody":"","fileTypesAndContributionMap":{"java":{"insertions":1,"deletions":1}}},{"hash":"3d8b61ac7b0d1f0f17c82eb658f91bf84b6c9401","isMergeCommit":false,"messageTitle":"Add class Event.java that inherits from class ToDo","messageBody":"","fileTypesAndContributionMap":{"java":{"insertions":17,"deletions":0}}},{"hash":"31b89ca863f54aacc1a10f725d2f7e16b79d9203","isMergeCommit":false,"messageTitle":"TaskMaster.java: Add addEvent method \u0026 Change unknownCommand method accordingly","messageBody":"","fileTypesAndContributionMap":{"java":{"insertions":30,"deletions":0}}},{"hash":"ab609097eddd9d7431962dbca156d893efdeef84","isMergeCommit":false,"messageTitle":"TaskMaster.java: Remove redundant input parameter of listTasks method","messageBody":"","tags":["Level-4","A-Inheritance"],"fileTypesAndContributionMap":{"java":{"insertions":3,"deletions":3}}},{"hash":"b2beb504125917f287c286a2f9f8adf1f2ac12de","isMergeCommit":false,"messageTitle":"TaskMaster.java: Refactor code to improve code quality","messageBody":"","tags":["A-CodeQuality"],"fileTypesAndContributionMap":{"java":{"insertions":54,"deletions":46}}},{"hash":"91ba4cf480640b206116bf09a18abca59eb467a7","isMergeCommit":false,"messageTitle":"TaskMaster.java: Move String manipulation code into respective methods","messageBody":"","fileTypesAndContributionMap":{"java":{"insertions":17,"deletions":4}}}]},{"date":"2025-08-31T00:00:00","commitResults":[{"hash":"61ffaf9d7682f11dc090696cab60f8a2499611a5","isMergeCommit":false,"messageTitle":"Update input.txt, EXPECTED.txt and runtest.bat to setup automated testing","messageBody":"","fileTypesAndContributionMap":{"txt":{"insertions":18,"deletions":0},"bat":{"insertions":1,"deletions":1}}},{"hash":"f28a37812a7ee6ad86af4fba2834ae5405bee94e","isMergeCommit":false,"messageTitle":"EXPECTED.TXT: Add empty line at the end of file TaskMaster.java: Text output changes to match EXPECTED.TXT Event.java: Text output changes to match EXPECTED.TXT","messageBody":"","fileTypesAndContributionMap":{"java":{"insertions":3,"deletions":3}}},{"hash":"21ff25f7706de032209b6ac11a25cfc37ec4e0d3","isMergeCommit":false,"messageTitle":"input.txt: Add 2 test cases, unknown command and bye command EXPECTED.TXT: Update to reflect the expected output of the 2 new test cases","messageBody":"","fileTypesAndContributionMap":{"txt":{"insertions":3,"deletions":1}}},{"hash":"931a3465f7f4dc053e6f1af3cf431a6bed563880","isMergeCommit":false,"messageTitle":"TaskMaster.java: Change to text output in endMessage method to match EXPECTED.TXT","messageBody":"","tags":["A-TextUiTesting"],"fileTypesAndContributionMap":{"java":{"insertions":1,"deletions":1}}}]},{"date":"2025-09-01T00:00:00","commitResults":[{"hash":"70f780574bc774228c4c2ab48455c3b00ed63ec4","isMergeCommit":false,"messageTitle":"TaskMaster.java: Refactor variables to not edit input parameters","messageBody":"","fileTypesAndContributionMap":{"java":{"insertions":13,"deletions":13}}}]},{"date":"2025-09-06T00:00:00","commitResults":[{"hash":"29580a8e63fa23728c90c2b3349edb602f9f0d5b","isMergeCommit":false,"messageTitle":"Deadline.java: Refactor code to meet coding standard","messageBody":"","fileTypesAndContributionMap":{"java":{"insertions":1,"deletions":1}}},{"hash":"613d074935cd567d7d2bc13f0dcd137f288cccb3","isMergeCommit":false,"messageTitle":"TaskMaster.java: Refactor code for better readability","messageBody":"","fileTypesAndContributionMap":{"java":{"insertions":8,"deletions":9}}},{"hash":"aa5b9a0fc9590a7d1eea05b9c29959600449a99d","isMergeCommit":false,"messageTitle":"Add MarkUnmarkOutOfBoundsException.java","messageBody":"","fileTypesAndContributionMap":{"java":{"insertions":3,"deletions":0}}},{"hash":"ec363790c8840e8bd42d5ed3d35558f8e76cd391","isMergeCommit":false,"messageTitle":"TaskMaster.java: throws MarkUnmarkOutOfBoundsException if user inputs non-exsisting index when marking \u0026 unmarking task and handles the exception","messageBody":"","fileTypesAndContributionMap":{"java":{"insertions":55,"deletions":30}}},{"hash":"b7aa18b91ea9f09b6fcf117b7754717b1cf1dfb7","isMergeCommit":false,"messageTitle":"Add test case of marking non-existing task","messageBody":"","fileTypesAndContributionMap":{"txt":{"insertions":1,"deletions":0},"java":{"insertions":1,"deletions":1}}},{"hash":"0928e90b8b2ff11f2eb1fe443a1e1bb2ce22e09a","isMergeCommit":false,"messageTitle":"Add EmptyTodoTaskException.java","messageBody":"","fileTypesAndContributionMap":{"java":{"insertions":3,"deletions":0}}},{"hash":"a785901fc3b063a771096020595bdc6902407fbb","isMergeCommit":false,"messageTitle":"TaskMaster.java: Throw EmptyTodoTaskException if user inputs empty field for todo task \u0026 handles the exception","messageBody":"","fileTypesAndContributionMap":{"java":{"insertions":21,"deletions":9}}},{"hash":"c9ffaf2f5e3ad1e766c5340dd074a0c33c11a302","isMergeCommit":false,"messageTitle":"Add test case for user leaving field for task blank when adding todo task","messageBody":"","fileTypesAndContributionMap":{"txt":{"insertions":1,"deletions":0}}},{"hash":"b68b5785385c6282a2406079d6b23321171041ed","isMergeCommit":false,"messageTitle":"Add DeadlineCommandMissingInputException.java","messageBody":"","fileTypesAndContributionMap":{"java":{"insertions":3,"deletions":0}}},{"hash":"cb239cda0b87a0be6c4fd349af928a6cc960c896","isMergeCommit":false,"messageTitle":"TaskMaster.java: Throws DeadlineCommandMissingInputException if user leaves field for \u003ctask\u003e and/or \u003cdeadline\u003e blank \u0026 handles the exception","messageBody":"","fileTypesAndContributionMap":{"java":{"insertions":21,"deletions":3}}},{"hash":"4db23abdccb8e844016186fed1981e284741778d","isMergeCommit":false,"messageTitle":"Add test case for missing inputs when adding a Deadline Task","messageBody":"","fileTypesAndContributionMap":{"txt":{"insertions":1,"deletions":0}}},{"hash":"dd0d9b7f3589dd1cf334c6f202af6dee8779c0df","isMergeCommit":false,"messageTitle":"Add EventCommandMissingInputException.java","messageBody":"","fileTypesAndContributionMap":{"java":{"insertions":3,"deletions":0}}},{"hash":"37cbfdf15845979429fe9cd28441a717c60c2d06","isMergeCommit":false,"messageTitle":"TaskMaster.java: Throws EventCommandMissingInputException if user leaves field for \u003ctask\u003e and/or \u003cfrom\u003e and/or \u003cto\u003e empty \u0026 handles the exception","messageBody":"","fileTypesAndContributionMap":{"java":{"insertions":30,"deletions":11}}},{"hash":"5c4301bda7f20e7f8aa0965c2c7a0162af7c9ee3","isMergeCommit":false,"messageTitle":"Add test cases for user leaving fields \u003ctask\u003e and/or \u003cfrom\u003e and/or \u003cto\u003e empty in event creation","messageBody":"","fileTypesAndContributionMap":{"txt":{"insertions":3,"deletions":0}}},{"hash":"d5b1eac69ffbf8aa30f7bc1665925ffe04ff3acc","isMergeCommit":false,"messageTitle":"TaskMaster.java: Change some text output \u0026 EXPECTED.TXT to fit new output","messageBody":"","fileTypesAndContributionMap":{"java":{"insertions":2,"deletions":2}}},{"hash":"8315c3ddd78d3ed3f85ca0eb77aa1953b017a60c","isMergeCommit":false,"messageTitle":"TaskMaster.java: Fix bug where task field for Deadline \u0026 Event creation was left empty and did not throw exceptions","messageBody":"","fileTypesAndContributionMap":{"java":{"insertions":6,"deletions":4}}},{"hash":"2f340ad304575c8750867f5a6535d245c7b18223","isMergeCommit":false,"messageTitle":"Add DeadlineCommandWrongSubCommand.java","messageBody":"","fileTypesAndContributionMap":{"java":{"insertions":3,"deletions":0}}},{"hash":"18f0efee353d5ca12130c3377424fc3e91e2b1aa","isMergeCommit":false,"messageTitle":"Add EventCommandWrongSubCommand.java","messageBody":"","fileTypesAndContributionMap":{"java":{"insertions":3,"deletions":0}}},{"hash":"b417728ae8f4898588a39380ed9b8577382f7dd1","isMergeCommit":false,"messageTitle":"TaskMaster.java: Throws handleDeadlineCommandWrongSubCommand if subcommand \"/by\" given during Deadline creation is missing or wrong \u0026 handles the exception","messageBody":"","fileTypesAndContributionMap":{"java":{"insertions":15,"deletions":2}}},{"hash":"4957e4515a02d9da4a7856113aaad293a14ddaaa","isMergeCommit":false,"messageTitle":"TaskMaster.java: Throws handleEventCommandWrongSubCommand if subcommand \"/from\" and/or \"/to\" is missng or incorrect \u0026 handles the exception","messageBody":"","fileTypesAndContributionMap":{"java":{"insertions":20,"deletions":3}}},{"hash":"e687127b4f7ca16ddc1b61e52872f9563197b20d","isMergeCommit":false,"messageTitle":"Refactor Exception Names to keep up with Coding Standards","messageBody":"","fileTypesAndContributionMap":{"java":{"insertions":19,"deletions":18}}},{"hash":"d8113f34a0790e5d591ae7f57a7fcccd53f89d0d","isMergeCommit":false,"messageTitle":"Add test cases for wrong subcommands when creating Deadline \u0026 Event","messageBody":"","tags":["A-Exceptions"],"fileTypesAndContributionMap":{"txt":{"insertions":3,"deletions":0}}},{"hash":"1265a2c7513afe15379422dc409730c6201d5381","isMergeCommit":true,"messageTitle":"Merge branch \u0027branch-Level-5\u0027","messageBody":"","tags":["Level-5"],"fileTypesAndContributionMap":{}}]},{"date":"2025-09-07T00:00:00","commitResults":[{"hash":"c8a072f7d254ccae9222342c5666e743c1490b35","isMergeCommit":false,"messageTitle":"Add Packages","messageBody":"","fileTypesAndContributionMap":{"java":{"insertions":31,"deletions":0},"bat":{"insertions":2,"deletions":2}}},{"hash":"1c0d7a9dd312b730c26dd0fdb073cf1338d52bbc","isMergeCommit":true,"messageTitle":"Merge branch \u0027branch-A-Packages\u0027","messageBody":"","tags":["A-Packages"],"fileTypesAndContributionMap":{}}]},{"date":"2025-09-13T00:00:00","commitResults":[{"hash":"5b23bece925e4ec950e0f8d1b95441d3ca0ae7eb","isMergeCommit":false,"messageTitle":"TaskMaster.java: Change from Array to ArrayList to store all tasks","messageBody":"","tags":["A-Collections"],"fileTypesAndContributionMap":{"java":{"insertions":24,"deletions":25}}},{"hash":"42d1932881e3792d32a2a0e813462fd8692b244a","isMergeCommit":false,"messageTitle":"TaskMaster.java: Add delete functionality with delete command","messageBody":"","fileTypesAndContributionMap":{"java":{"insertions":31,"deletions":0}}},{"hash":"2bc07754400c1739e839fe287ac72ae3db41f70e","isMergeCommit":false,"messageTitle":"Add DeleteCommandMissingInputException.java","messageBody":"","fileTypesAndContributionMap":{"java":{"insertions":5,"deletions":0}}},{"hash":"21393000dd428f9026812287958d2e431b1304d8","isMergeCommit":false,"messageTitle":"Add DeleteCommandOutOfBoundsException.java","messageBody":"","fileTypesAndContributionMap":{"java":{"insertions":5,"deletions":0}}},{"hash":"09b05a80c329dbaf6821a05938a49fe42214d41a","isMergeCommit":false,"messageTitle":"TaskMaster.java \u0026 EXPECTED.TXT: Change unknown command output to include delete command","messageBody":"","fileTypesAndContributionMap":{"java":{"insertions":1,"deletions":0}}},{"hash":"2017a9b9914b094a4f48c3349ac693303565fe22","isMergeCommit":false,"messageTitle":"TaskMaster.java: Throws deleteCommandMissingInputException if delete command has no other inputs and handles it \u0026 Throws deleteCommandOutOfBoundsException if user tries to delete non-existing task and handles it","messageBody":"","fileTypesAndContributionMap":{"java":{"insertions":45,"deletions":13}}},{"hash":"1b9d89e1eb4cab69dc5bf9ef0ee93b574b3bff82","isMergeCommit":false,"messageTitle":"Add MarkCommandMissingInputException.java","messageBody":"","fileTypesAndContributionMap":{"java":{"insertions":5,"deletions":0}}},{"hash":"ae80722e08fe71a83100d295f8fbedccec0a1793","isMergeCommit":false,"messageTitle":"Add UnmarkCommandMissingInputException.java","messageBody":"","fileTypesAndContributionMap":{"java":{"insertions":5,"deletions":0}}},{"hash":"a93f363ed1d74ce8e663714877286860f0dcb9d1","isMergeCommit":false,"messageTitle":"TaskMaster.java: Throw MarkCommandMissingInputException or UnmarkCommandMissingInputException if mark or unmark command does not have other parameters and handles the exceptions","messageBody":"","fileTypesAndContributionMap":{"java":{"insertions":43,"deletions":5}}},{"hash":"ba8fd7ba726cce674353e03f0122000de7728bd7","isMergeCommit":false,"messageTitle":"Add test cases for missing inputs for commands: mark, unmark, delete \u0026 Add test cases for delete non-existing task","messageBody":"","fileTypesAndContributionMap":{"txt":{"insertions":13,"deletions":0}}},{"hash":"7ba98d15e12a490a6a705565220560c665865ac9","isMergeCommit":false,"messageTitle":"TaskMaster.Java: Reorder methods","messageBody":"","fileTypesAndContributionMap":{"java":{"insertions":33,"deletions":33}}},{"hash":"aae2a878bd5a0ba5f224497887cf428d20433eee","isMergeCommit":false,"messageTitle":"Add DeleteCommandTooManyInputException.java \u0026 MarkCommandTooManyInputException.java \u0026 UnmarkCommandTooManyInputException.java","messageBody":"","fileTypesAndContributionMap":{"java":{"insertions":15,"deletions":0}}},{"hash":"2d23ed3507eec53fa75597d062fcc5f29c7fe1f2","isMergeCommit":false,"messageTitle":"TaskMaster.java: Throw DeleteCommandTooManyInputException, MarkCommandTooManyInputException, UnmarkCommandTooManyInputException if too many inputs for commands: delete, mark, unmark and handles the exceptions","messageBody":"","fileTypesAndContributionMap":{"java":{"insertions":51,"deletions":7}}},{"hash":"6d1933570d9f7b8a838a29afcfc8a8602e371209","isMergeCommit":false,"messageTitle":"TaskMaster.java: Fix bug DeleteCommandTooManyInputException was not being thrown as intended","messageBody":"","fileTypesAndContributionMap":{"java":{"insertions":8,"deletions":2}}},{"hash":"5a9167052905068741ddde6091e6eb011b439d69","isMergeCommit":false,"messageTitle":"Add test cases for too many inputs for commands: mark, unmark, delete","messageBody":"","fileTypesAndContributionMap":{"txt":{"insertions":4,"deletions":0}}}]},{"date":"2025-09-14T00:00:00","commitResults":[{"hash":"e4815aed34319eb42db7c1a7056f54ba95326e35","isMergeCommit":false,"messageTitle":"TaskMaster.java: Add function to read from and export to text file containing data (src/main/java/taskmaster/data/TaskMaster.txt)","messageBody":"","fileTypesAndContributionMap":{"java":{"insertions":137,"deletions":2}}},{"hash":"4b3f755965685e0c2d4d791332c80fabc177fc64","isMergeCommit":true,"messageTitle":"Merge branch \u0027branch-Level-6\u0027","messageBody":"","tags":["Level-6"],"fileTypesAndContributionMap":{}},{"hash":"82a3a7b6b92a1931d7cb9661f6ec061d19e5bdc8","isMergeCommit":true,"messageTitle":"Merge branch \u0027branch-Level-7\u0027","messageBody":"# Conflicts:\n#\tsrc/main/java/taskmaster/TaskMaster.java\n","tags":["Level-7"],"fileTypesAndContributionMap":{}},{"hash":"84bd701e53990ed87cdaddde9113bf2ca567be2a","isMergeCommit":false,"messageTitle":"TaskMaster.java \u0026 EXPECTED.TXT: Change some text output","messageBody":"","fileTypesAndContributionMap":{"java":{"insertions":3,"deletions":4}}},{"hash":"2eee3dde403d6190e2520cba88a09828f4967f8d","isMergeCommit":false,"messageTitle":"Change file path for data file","messageBody":"","fileTypesAndContributionMap":{"java":{"insertions":1,"deletions":1}}},{"hash":"fecca9be26e5b909f47a134740c4dbf4f07953e9","isMergeCommit":false,"messageTitle":"TaskMaster.java: Add ability to create directory \u0026 file if does not exist","messageBody":"","fileTypesAndContributionMap":{"java":{"insertions":11,"deletions":2}}},{"hash":"e73054abed0509b0572a66ec08f2c44e5e7276e3","isMergeCommit":false,"messageTitle":"Change some test cases and expected outputs","messageBody":"","tags":["A-Jar"],"fileTypesAndContributionMap":{"txt":{"insertions":2,"deletions":0}}}]},{"date":"2025-09-19T00:00:00","commitResults":[{"hash":"55d33bba1b20435c4ad511a22b56372751f1b146","isMergeCommit":false,"messageTitle":"TaskMaster.java: Refactor code","messageBody":"","fileTypesAndContributionMap":{"java":{"insertions":113,"deletions":108}}}]},{"date":"2025-09-20T00:00:00","commitResults":[{"hash":"efcd7e45231314ed8816c1a09e4972384bdd6d1c","isMergeCommit":false,"messageTitle":"Task.java: Add get methods and change numberOfTasks availability","messageBody":"","fileTypesAndContributionMap":{"java":{"insertions":9,"deletions":1}}},{"hash":"71c4a9b1a13c3e4a42bdf557d950e74301e61be4","isMergeCommit":false,"messageTitle":"Add Storage.java","messageBody":"","fileTypesAndContributionMap":{"java":{"insertions":112,"deletions":0}}},{"hash":"23f89db2c99e9690616b0a4e4d4823bf0cfca58d","isMergeCommit":false,"messageTitle":"TaskMaster.java: Use Storage class","messageBody":"","fileTypesAndContributionMap":{"java":{"insertions":9,"deletions":103}}},{"hash":"d14465e7e4c530219a6815fa339eb99b540c0f22","isMergeCommit":false,"messageTitle":"Add Ui.java","messageBody":"","fileTypesAndContributionMap":{"java":{"insertions":161,"deletions":0}}},{"hash":"46391941e54cff2224f1f916164cbb269e1091a3","isMergeCommit":false,"messageTitle":"TaskMaster.java: Use Ui.java","messageBody":"","fileTypesAndContributionMap":{"java":{"insertions":26,"deletions":162}}},{"hash":"27f2ae17213c500820b6213591ac957efe01f2c4","isMergeCommit":false,"messageTitle":"Ui.java: Add new outputs","messageBody":"","fileTypesAndContributionMap":{"java":{"insertions":26,"deletions":4}}},{"hash":"6751eeb95caf57f3972793b466659acd982df013","isMergeCommit":false,"messageTitle":"Add Parser.java \u0026 TaskList.java","messageBody":"","fileTypesAndContributionMap":{"java":{"insertions":348,"deletions":0}}},{"hash":"493c99fb6254625626499157d0fd6031018987ea","isMergeCommit":false,"messageTitle":"TaskMaster.java: Use TaskList \u0026 Parser classes","messageBody":"","fileTypesAndContributionMap":{"java":{"insertions":8,"deletions":316}}},{"hash":"0352da84cd2bd5e9504d1fdec7eeb56f3d477e5c","isMergeCommit":false,"messageTitle":"TaskMaster.java: Refactor code","messageBody":"","fileTypesAndContributionMap":{"java":{"insertions":3,"deletions":11}}},{"hash":"aae78c9b4b80079c32bbecf767a78d60fee783e9","isMergeCommit":false,"messageTitle":"Remove uncessary code \u0026 comments","messageBody":"","tags":["A-MoreOOP"],"fileTypesAndContributionMap":{"java":{"insertions":27,"deletions":55}}},{"hash":"584e42138dff784782f265c9c0a3e244846ca66d","isMergeCommit":false,"messageTitle":"Add command to find with keyword","messageBody":"","fileTypesAndContributionMap":{"java":{"insertions":43,"deletions":0}}},{"hash":"7e40d05a50510031d882161879505f2f1145f0d2","isMergeCommit":false,"messageTitle":"Add test case for find command","messageBody":"","fileTypesAndContributionMap":{"txt":{"insertions":1,"deletions":0}}},{"hash":"14f02a904b80e9489c4af8b50de66a6332bfd13e","isMergeCommit":false,"messageTitle":"Add FindCommandMissingInputException.java","messageBody":"","fileTypesAndContributionMap":{"java":{"insertions":5,"deletions":0}}},{"hash":"3aabcf49b7f3bb2caba4041888c4785492ec0b92","isMergeCommit":false,"messageTitle":"Throw and Handle FindCommandMissingInputException","messageBody":"","fileTypesAndContributionMap":{"java":{"insertions":44,"deletions":16}}},{"hash":"23fda6bd64b2a2f0539aa46092af997cdb97f385","isMergeCommit":false,"messageTitle":"Add test case for find command missing keyword","messageBody":"","fileTypesAndContributionMap":{"txt":{"insertions":1,"deletions":0}}},{"hash":"5739506fcad355ea3080ccdfb91f37b41732b1be","isMergeCommit":true,"messageTitle":"Merge branch \u0027branch-Level-9\u0027","messageBody":"","tags":["Level-9"],"fileTypesAndContributionMap":{}}]},{"date":"2025-09-21T00:00:00","commitResults":[{"hash":"ff40ee532725d1d3a894f0737c793b3cb32d1cc4","isMergeCommit":false,"messageTitle":"Add JavaDoc comments","messageBody":"","fileTypesAndContributionMap":{"java":{"insertions":255,"deletions":18}}},{"hash":"4b20379e55dbcb9d8a839c1a259d364bbfba50db","isMergeCommit":true,"messageTitle":"Merge pull request #1 from Emannuel-Tan/branch-A-JavaDoc","messageBody":"Add JavaDoc comments","tags":["A-JavaDoc"],"fileTypesAndContributionMap":{}},{"hash":"050ed5df98c3482c10a6b0e82c08562e60eb5ab7","isMergeCommit":false,"messageTitle":"Update README.md","messageBody":"","fileTypesAndContributionMap":{"md":{"insertions":21,"deletions":22}}},{"hash":"11543ae3cc1d853dadc1616af10708a3436a5907","isMergeCommit":false,"messageTitle":"Update README.md","messageBody":"","fileTypesAndContributionMap":{"md":{"insertions":9,"deletions":5}}},{"hash":"cf9b3a83d590832a4b00fb27b54b227110c42242","isMergeCommit":false,"messageTitle":"Update README.md","messageBody":"","fileTypesAndContributionMap":{"md":{"insertions":8,"deletions":8}}},{"hash":"f0f6bfd2ca4359d862a70aa72ce7356365c7c7fa","isMergeCommit":false,"messageTitle":"Update README.md","messageBody":"","fileTypesAndContributionMap":{"md":{"insertions":67,"deletions":5}}},{"hash":"be25eff9c45cdf2c494714a8281dee4c1736bbcc","isMergeCommit":false,"messageTitle":"Update README.md","messageBody":"","fileTypesAndContributionMap":{"md":{"insertions":15,"deletions":13}}},{"hash":"e4323e55c49a3ce566f66140d4dc646818597390","isMergeCommit":false,"messageTitle":"Add image to README.md","messageBody":"","fileTypesAndContributionMap":{"md":{"insertions":1,"deletions":1}}},{"hash":"94db38902b6dc32ae4929b1a47869472fe116857","isMergeCommit":false,"messageTitle":"Revert Add image to README.md","messageBody":"","tags":["A-UserGuide"],"fileTypesAndContributionMap":{"md":{"insertions":1,"deletions":3}}},{"hash":"82df1981b39b6b08ef2eea6306826e77eafea22e","isMergeCommit":false,"messageTitle":"Add date formatting for deadline command and respective test cases","messageBody":"","fileTypesAndContributionMap":{"txt":{"insertions":7,"deletions":0},"java":{"insertions":86,"deletions":6}}},{"hash":"e5f012ca058aa286cc72b43642f1951fe676ba32","isMergeCommit":false,"messageTitle":"Add date formatting for event command and respective test cases","messageBody":"","fileTypesAndContributionMap":{"txt":{"insertions":10,"deletions":0},"java":{"insertions":95,"deletions":15}}},{"hash":"ca50d3c1a430ad1d2ef7ed921b9c7283507a351c","isMergeCommit":false,"messageTitle":"Update README.md","messageBody":"","fileTypesAndContributionMap":{"md":{"insertions":8,"deletions":4}}},{"hash":"f0d290872e559733057b3169605bc79d1e55f777","isMergeCommit":true,"messageTitle":"Merge pull request #2 from Emannuel-Tan/branch-Level-8","messageBody":"Add date support to deadline \u0026 event command","tags":["Level-8"],"fileTypesAndContributionMap":{}},{"hash":"af08aca0dbb22286c57a93e5e6f67f6a54bf7d1e","isMergeCommit":false,"messageTitle":"Fix a typo in README.md","messageBody":"","fileTypesAndContributionMap":{"md":{"insertions":1,"deletions":1}}},{"hash":"605b374a1624b2071f32978a522c7a8b52d6c261","isMergeCommit":false,"messageTitle":"Update README.md","messageBody":"","tags":["A-Release"],"fileTypesAndContributionMap":{"md":{"insertions":1,"deletions":1}}}]},{"date":"2025-09-24T00:00:00","commitResults":[{"hash":"80e8a2c24d51276626132cf747e6b879dc4091a5","isMergeCommit":false,"messageTitle":"Refactor Code","messageBody":"","fileTypesAndContributionMap":{"java":{"insertions":160,"deletions":207}}}]}]},"authorFileTypeContributionMap":{"Emannuel-Tan":{"java":1282,"md":85,"fxml":0,"sh":0,"bat":2,"gradle":0,"txt":67}},"authorContributionVariance":{"Emannuel-Tan":61318.605},"authorDisplayNameMap":{"Emannuel-Tan":"CS2113-T10-1 EMAN.. YUE"}}
