{"authorDailyContributionsMap":{"enwei29":[{"date":"2025-08-22T00:00:00","commitResults":[{"hash":"0a9318be8259a39e33bb6fc6ae00f1dc7817678f","isMergeCommit":false,"messageTitle":"Complete Level-0 - rename Duke to Bob, add greeting and exit flow","messageBody":"","fileTypesAndContributionMap":{"java":{"insertions":18,"deletions":0}}},{"hash":"de42bf655336f580ee243b1de1b3ec19f5780a51","isMergeCommit":false,"messageTitle":"Complete Level 0 — rename Duke to Bob, add greeting and exit flow","messageBody":"","tags":["Level-0"],"fileTypesAndContributionMap":{"java":{"insertions":0,"deletions":10}}}]},{"date":"2025-08-25T00:00:00","commitResults":[{"hash":"54012bff1e5674837441dae7bcf7f18e17069371","isMergeCommit":false,"messageTitle":"Implement echo loop and terminate on \"bye\"","messageBody":"","tags":["Level-1"],"fileTypesAndContributionMap":{"java":{"insertions":27,"deletions":10}}},{"hash":"7a5d4181fa1c684111e11f9655d6e8c9c565e1bd","isMergeCommit":false,"messageTitle":"Implement add and list functionality for chatbot","messageBody":"","tags":["Level-2"],"fileTypesAndContributionMap":{"java":{"insertions":15,"deletions":3}}}]},{"date":"2025-08-29T00:00:00","commitResults":[{"hash":"96012eae9d2fc807454dbbecc535b4e8320dd6e6","isMergeCommit":false,"messageTitle":"Add the ability to mark tasks as done","messageBody":"","tags":["Level-3","A-CodingStandard"],"fileTypesAndContributionMap":{"java":{"insertions":55,"deletions":12}}}]},{"date":"2025-09-07T00:00:00","commitResults":[{"hash":"f8d8b288c19b57e0bf18f4c89b13449747d07bd9","isMergeCommit":false,"messageTitle":"Support todo tasks, deadlines and events with start-end dates","messageBody":"","tags":["Level-4"],"fileTypesAndContributionMap":{"java":{"insertions":112,"deletions":16}}},{"hash":"26e03ed4309726d1b555434b412023922b4738dd","isMergeCommit":false,"messageTitle":"Move Scanner out of loop and use toString() in list","messageBody":"","tags":["A-CodeQuality"],"fileTypesAndContributionMap":{"java":{"insertions":12,"deletions":28}}}]},{"date":"2025-09-08T00:00:00","commitResults":[{"hash":"b05e0eac71cbb13225111de6dcd1f8c30ffa4272","isMergeCommit":false,"messageTitle":"Add error handling for empty tasks and unknown commands","messageBody":"","fileTypesAndContributionMap":{"java":{"insertions":113,"deletions":56}}},{"hash":"eec4dfad3391a6db84be517b3c406ec339914825","isMergeCommit":true,"messageTitle":"Merge branch-Level-5 (Level-5 increment)","messageBody":"","tags":["Level-5","A-Exceptions"],"fileTypesAndContributionMap":{}}]},{"date":"2025-09-10T00:00:00","commitResults":[{"hash":"119fe36b5a198f3fea96d7e3f6bfd297161322f1","isMergeCommit":true,"messageTitle":"Merge pull request #1 from enwei29/branch-Level-5","messageBody":"Add error handling for empty tasks and unknown commands","fileTypesAndContributionMap":{}}]},{"date":"2025-09-19T00:00:00","commitResults":[{"hash":"75833a94ca370480ca9104bbb2d36febdfe7cc70","isMergeCommit":false,"messageTitle":"Add functionality to delete tasks from list","messageBody":"","fileTypesAndContributionMap":{"java":{"insertions":13,"deletions":2}}},{"hash":"e5ea154fac8ac2bb7e4e306166e4b1f3931e5e03","isMergeCommit":false,"messageTitle":"Add functionality to save tasks into hard disk automatically when task list changes","messageBody":"","fileTypesAndContributionMap":{"txt":{"insertions":0,"deletions":0},"java":{"insertions":89,"deletions":2}}},{"hash":"0205318b157709af6009a9bdaa9291312a3e293c","isMergeCommit":true,"messageTitle":"Merge Level-6","messageBody":"","fileTypesAndContributionMap":{}},{"hash":"5023f37b11389ec60e25de06f5fcf6b4e1c119dc","isMergeCommit":true,"messageTitle":"Merge branch \u0027master\u0027 of https://github.com/enwei29/ip","messageBody":"","tags":["Level-6"],"fileTypesAndContributionMap":{}},{"hash":"3fdf5c5dca8204429216f03d11e1062d308d590b","isMergeCommit":true,"messageTitle":"Merge Level-7 with master","messageBody":"","tags":["Level-7","A-Jar","A-Collections"],"fileTypesAndContributionMap":{}}]},{"date":"2025-09-30T00:00:00","commitResults":[{"hash":"815628927a0ccb1472c2fdc4c2ef39d1350a224d","isMergeCommit":false,"messageTitle":"Give users a way to find a task by searching for a keyword in the task description","messageBody":"","tags":["Level-9"],"fileTypesAndContributionMap":{"java":{"insertions":31,"deletions":2}}},{"hash":"401f8b8745647fbc175740f521bb22b012ee1239","isMergeCommit":true,"messageTitle":"Merge pull request #2 from enwei29/branch-Level-9","messageBody":"Give users a way to find a task by searching for a keyword in the task description","fileTypesAndContributionMap":{}}]},{"date":"2025-10-03T00:00:00","commitResults":[{"hash":"e7233ba2583008690da7c9340f85deceab0571e8","isMergeCommit":false,"messageTitle":"Refactor code to extract out closely related code as class, including Ui, Storage, Parser and TaskList","messageBody":"","fileTypesAndContributionMap":{"java":{"insertions":302,"deletions":207}}},{"hash":"6a59f983f695f2336f6da1cbbc958c141af16ca3","isMergeCommit":true,"messageTitle":"Merge remote-tracking branch \u0027origin/master\u0027","messageBody":"# Conflicts:\n#\tsrc/main/java/Bob.java\n","tags":["A-MoreOOP"],"fileTypesAndContributionMap":{}},{"hash":"334a7e6d0b5484b3f0d0658c28b4476eb6309224","isMergeCommit":false,"messageTitle":"Add JavaDoc comments to the code","messageBody":"","tags":["A-JavaDoc"],"fileTypesAndContributionMap":{"java":{"insertions":40,"deletions":0}}},{"hash":"14e7f34db50aa61f35ea9944368b4f139ba03744","isMergeCommit":false,"messageTitle":"Add JavaDoc comments to the code","messageBody":"","fileTypesAndContributionMap":{"java":{"insertions":110,"deletions":14}}},{"hash":"369b2bd50860577b21a806e6cde8501e11541a66","isMergeCommit":false,"messageTitle":"Update README.md","messageBody":"","fileTypesAndContributionMap":{"md":{"insertions":123,"deletions":11}}},{"hash":"8dc2e16c19e2d252e8746c6b60bcabac540b39c3","isMergeCommit":true,"messageTitle":"Merge pull request #3 from enwei29/branch-A-JavaDoc","messageBody":"Merge JavaDoc Comments","fileTypesAndContributionMap":{}},{"hash":"220a5d1ef1847001d752fcb05f608debc75c94f5","isMergeCommit":false,"messageTitle":"Update README.md","messageBody":"","tags":["A-UserGuide"],"fileTypesAndContributionMap":{"md":{"insertions":109,"deletions":14}}},{"hash":"ba3f6d6e0dc5cd0416367de08235852a7d77f752","isMergeCommit":false,"messageTitle":"Update README.md","messageBody":"","tags":["A-Release"],"fileTypesAndContributionMap":{"md":{"insertions":0,"deletions":2}}}]}]},"authorFileTypeContributionMap":{"enwei29":{"java":556,"md":222,"fxml":0,"sh":0,"bat":0,"gradle":0,"txt":0}},"authorContributionVariance":{"enwei29":15849.941},"authorDisplayNameMap":{"enwei29":"CS2113-W13-4 CHEW.. WEI"}}
